README.md
setup.py
xmqt/__init__.py
xmqt/dd.py
xmqt/dingtalkboot.py
xmqt/quantify_xoenmap.py
xmqt/sarindicator.py
xmqt/test.py
xmqt/test2.py
xmqt.egg-info/PKG-INFO
xmqt.egg-info/SOURCES.txt
xmqt.egg-info/dependency_links.txt
xmqt.egg-info/top_level.txt