Metadata-Version: 1.2
Name: xmqt
Version: 2.0.1
Summary: Pyhont Qt Basic Module  -->公众号：Python 量化基础库
Home-page: http://xoenmap.icu/
Author: bobzhangfw
Author-email: bobzhangfw@163.com
License: UNKNOWN
Platform: UNKNOWN
Requires-Python: >=3.5.0
